facile_trigger_helper_easy/__init__.py
facile_trigger_helper_easy/facile_trigger_helper_easy.py
facile_gitlab_trigger_easy-0.0.0.1.dist-info/METADATA
facile_gitlab_trigger_easy-0.0.0.1.dist-info/WHEEL
facile_gitlab_trigger_easy-0.0.0.1.dist-info/entry_points.txt
facile_gitlab_trigger_easy-0.0.0.1.dist-info/top_level.txt
facile_gitlab_trigger_easy-0.0.0.1.dist-info/RECORD
