Metadata-Version: 2.1
Name: facile-gitlab-trigger-easy
Version: 0.0.0.1
Summary: testing 
Home-page: https://www.facile.it
Author: Fabio Lima, oxidation
Author-email: f46io@icloud.com, agubellini@yahoo.com
License: UNKNOWN
Platform: any
Requires-Dist: python-gitlab (~=2.2.0)
Requires-Dist: typing (~=3.7.4.1)
Requires-Dist: requests-mock (~=1.7.0)
Requires-Dist: ansicolors (~=1.1.8)
